netlify/__init__.py
netlify/__main__.py
netlify/client.py
netlify/enums.py
netlify/exceptions.py
netlify/py.typed
netlify/pydantic_polyfill.py
netlify/schemas.py
netlify/transport.py
netlify/auth/__init__.py
netlify/auth/bearer.py
netlify_python-0.4.0.dist-info/licenses/LICENSE
netlify_python-0.4.0.dist-info/METADATA
netlify_python-0.4.0.dist-info/WHEEL
netlify_python-0.4.0.dist-info/top_level.txt
netlify_python-0.4.0.dist-info/RECORD
