Metadata-Version: 2.4
Name: netlify-python
Version: 0.4.0
Summary: Bare-bones python library for the official Netlify API
Author-email: cbrews <cbrews@users.noreply.github.com>
License: MIT
Keywords: http,netlify,client-library
Classifier: Development Status :: 3 - Alpha
Classifier: Intended Audience :: Developers
Classifier: Topic :: Software Development :: Libraries
Classifier: Programming Language :: Python :: 3.10
Classifier: Programming Language :: Python :: 3.11
Classifier: Programming Language :: Python :: 3.12
Classifier: Programming Language :: Python :: 3.13
Classifier: Programming Language :: Python :: 3.14
Classifier: License :: OSI Approved :: MIT License
Classifier: Framework :: Pydantic :: 1
Classifier: Framework :: Pydantic :: 2
Requires-Python: >=3.10
License-File: LICENSE
Requires-Dist: httpx>=0.23.0
Requires-Dist: python-dateutil>=2.8.2
Requires-Dist: pydantic>=1; python_version < "3.14"
Requires-Dist: pydantic>=2; python_version >= "3.14"
Provides-Extra: dev
Requires-Dist: httpx==0.28.1; extra == "dev"
Requires-Dist: mypy==1.18.2; extra == "dev"
Requires-Dist: ruff==0.14.4; extra == "dev"
Requires-Dist: pytest==8.4.2; extra == "dev"
Requires-Dist: python-dateutil==2.9.0.post0; extra == "dev"
Requires-Dist: types-python-dateutil==2.9.0.20251108; extra == "dev"
Requires-Dist: pytest-cov==7.0.0; extra == "dev"
Requires-Dist: pytest-httpx==0.35.0; extra == "dev"
Requires-Dist: pre-commit==4.4.0; extra == "dev"
Requires-Dist: pytest-mock==3.15.1; extra == "dev"
Provides-Extra: build
Requires-Dist: build; extra == "build"
Requires-Dist: twine; extra == "build"
Dynamic: license-file
